semra/.DS_Store
semra/__init__.py
semra/__main__.py
semra/api.py
semra/cli.py
semra/client.py
semra/database.py
semra/gilda_utils.py
semra/inference.py
semra/io/__init__.py
semra/io/graph.py
semra/io/io.py
semra/io/io_utils.py
semra/io/neo4j_io.py
semra/io/templates/Dockerfile
semra/io/templates/run_on_startup.sh
semra/io/templates/startup.sh
semra/landscape/__init__.py
semra/landscape/__main__.py
semra/landscape/anatomy.py
semra/landscape/cells.py
semra/landscape/cli.py
semra/landscape/complexes.py
semra/landscape/diseases.py
semra/landscape/genes.py
semra/landscape/taxrank.py
semra/landscape/utils.py
semra/pipeline.py
semra/py.typed
semra/rules.py
semra/sources/__init__.py
semra/sources/__main__.py
semra/sources/biopragmatics.py
semra/sources/cbms2019.py
semra/sources/cli.py
semra/sources/clo.py
semra/sources/compath.py
semra/sources/famplex.py
semra/sources/gilda.py
semra/sources/intact.py
semra/sources/ncit.py
semra/sources/omim.py
semra/sources/pubchem.py
semra/sources/wikidata.py
semra/struct.py
semra/templates/base.html
semra/templates/concept.html
semra/templates/home.html
semra/templates/mapping.html
semra/templates/mapping_set.html
semra/templates/utils.html
semra/utils.py
semra/version.py
semra/web/__init__.py
semra/web/fastapi_components.py
semra/web/flask_components.py
semra/web/shared.py
semra/wsgi.py
semra-0.1.3.dist-info/licenses/LICENSE
semra-0.1.3.dist-info/WHEEL
semra-0.1.3.dist-info/entry_points.txt
semra-0.1.3.dist-info/METADATA
semra-0.1.3.dist-info/RECORD
