Metadata-Version: 2.4
Name: semra
Version: 0.1.3
Summary: Semantic mapping reasoner and assembler
Keywords: snekpack,cookiecutter,sssom,semantic mappings,ontology merging,ontology mappings
Author: Charles Tapley Hoyt
Author-email: Charles Tapley Hoyt <cthoyt@gmail.com>
License-File: LICENSE
Classifier: Development Status :: 4 - Beta
Classifier: Environment :: Console
Classifier: Intended Audience :: Developers
Classifier: License :: OSI Approved :: MIT License
Classifier: Operating System :: OS Independent
Classifier: Framework :: Pytest
Classifier: Framework :: tox
Classifier: Framework :: Sphinx
Classifier: Natural Language :: English
Classifier: Programming Language :: Python
Classifier: Programming Language :: Python :: 3.10
Classifier: Programming Language :: Python :: 3.11
Classifier: Programming Language :: Python :: 3.12
Classifier: Programming Language :: Python :: 3.13
Classifier: Programming Language :: Python :: 3 :: Only
Classifier: Typing :: Typed
Requires-Dist: pystow
Requires-Dist: pandas
Requires-Dist: pydantic
Requires-Dist: tqdm
Requires-Dist: more-itertools
Requires-Dist: networkx
Requires-Dist: bioregistry>=0.12.7
Requires-Dist: pyobo>=0.12.2
Requires-Dist: bioontologies>=0.7.2
Requires-Dist: typing-extensions
Requires-Dist: zenodo-client
Requires-Dist: ssslm
Requires-Dist: curies>=0.10.16
Requires-Dist: jinja2
Requires-Dist: class-resolver>=0.6.0
Requires-Dist: pyyaml
Requires-Dist: sphinx>=8 ; extra == 'docs'
Requires-Dist: sphinx-rtd-theme>=3.0 ; extra == 'docs'
Requires-Dist: sphinx-click ; extra == 'docs'
Requires-Dist: sphinx-automodapi ; extra == 'docs'
Requires-Dist: autodoc-pydantic ; extra == 'docs'
Requires-Dist: texext ; extra == 'docs'
Requires-Dist: ipython ; extra == 'landscape-notebooks'
Requires-Dist: jupyter ; extra == 'landscape-notebooks'
Requires-Dist: upsetplot ; extra == 'landscape-notebooks'
Requires-Dist: seaborn ; extra == 'landscape-notebooks'
Requires-Dist: matplotlib ; extra == 'landscape-notebooks'
Requires-Dist: pygraphviz ; extra == 'landscape-notebooks'
Requires-Dist: pytest ; extra == 'tests'
Requires-Dist: coverage[toml] ; extra == 'tests'
Requires-Dist: sssom>=0.4.16 ; extra == 'tests'
Requires-Dist: httpx ; extra == 'tests'
Requires-Dist: fastapi ; extra == 'web'
Requires-Dist: uvicorn ; extra == 'web'
Requires-Dist: flask ; extra == 'web'
Requires-Dist: bootstrap-flask ; extra == 'web'
Requires-Dist: neo4j ; extra == 'web'
Requires-Dist: biomappings ; extra == 'web'
Maintainer: Charles Tapley Hoyt
Maintainer-email: Charles Tapley Hoyt <cthoyt@gmail.com>
Requires-Python: >=3.10
Project-URL: Bug Tracker, https://github.com/biopragmatics/semra/issues
Project-URL: Documentation, https://semra.readthedocs.io
Project-URL: Funding, https://github.com/sponsors/cthoyt
Project-URL: Homepage, https://github.com/biopragmatics/semra
Project-URL: Repository, https://github.com/biopragmatics/semra.git
Provides-Extra: docs
Provides-Extra: landscape-notebooks
Provides-Extra: tests
Provides-Extra: web
